accounts/__init__.py
accounts/api_urls.py
accounts/api_views.py
accounts/apps.py
accounts/models.py
accounts/serializer.py
accounts/swagger_params.py
accounts/tasks.py
accounts/tests_celery_tasks.py
accounts/migrations/0001_initial.py
accounts/migrations/0002_auto_20190128_1237.py
accounts/migrations/0003_auto_20190201_1840.py
accounts/migrations/0004_account_status.py
accounts/migrations/0005_auto_20190212_1334.py
accounts/migrations/0006_auto_20190212_1708.py
accounts/migrations/0007_email.py
accounts/migrations/0008_account_assigned_to.py
accounts/migrations/0009_auto_20190809_1659.py
accounts/migrations/0010_account_teams.py
accounts/migrations/0011_account_company.py
accounts/migrations/0012_remove_account_company.py
accounts/migrations/__init__.py
cases/__init__.py
cases/api_urls.py
cases/api_views.py
cases/apps.py
cases/models.py
cases/serializer.py
cases/swagger_params.py
cases/tasks.py
cases/tests_celery_tasks.py
cases/migrations/0001_initial.py
cases/migrations/0002_auto_20190128_1237.py
cases/migrations/0003_auto_20190212_1334.py
cases/migrations/0004_case_teams.py
cases/migrations/0005_case_company.py
cases/migrations/0006_auto_20210323_1747.py
cases/migrations/0007_remove_case_company.py
cases/migrations/__init__.py
common/__init__.py
common/access_decorators_mixins.py
common/admin.py
common/api_urls.py
common/api_views.py
common/apps.py
common/custom_auth.py
common/models.py
common/serializer.py
common/status.py
common/swagger_params.py
common/tasks.py
common/tests_celery_tasks.py
common/token_generator.py
common/utils.py
common/app_urls/__init__.py
common/context_processors/__init__.py
common/context_processors/common.py
common/middleware/__init__.py
common/migrations/0001_initial.py
common/migrations/0002_auto_20190128_1237.py
common/migrations/0003_document.py
common/migrations/0004_attachments_case.py
common/migrations/0005_auto_20190204_1400.py
common/migrations/0006_comment_user.py
common/migrations/0007_auto_20190212_1334.py
django_crm-0.9.0.dist-info/LICENSE
django_crm-0.9.0.dist-info/METADATA
django_crm-0.9.0.dist-info/WHEEL
django_crm-0.9.0.dist-info/top_level.txt
django_crm-0.9.0.dist-info/RECORD
