Metadata-Version: 2.1
Name: django-crm
Version: 0.9.0
Summary: An opensourse CRM developed on django framework
Home-page: https://github.com/MicroPyramid/Django-CRM.git
Author: Micropyramid
Author-email: hello@micropyramid.com
License: UNKNOWN
Platform: UNKNOWN
Classifier: Development Status :: 4 - Beta
Classifier: Framework :: Django
Classifier: License :: OSI Approved :: MIT License
Classifier: Programming Language :: Python
Classifier: Programming Language :: Python :: 3
Classifier: Programming Language :: Python :: 3.2
Classifier: Programming Language :: Python :: 3.3
Classifier: Programming Language :: Python :: 3.4
Classifier: Programming Language :: Python :: 3.5
Classifier: Programming Language :: Python :: 3.6
License-File: LICENSE
